carrot_mc/__init__.py
carrot_mc/backend.py
carrot_mc/carrot.py
carrot_mc/cli.py
carrot_mc/cli_printer.py
carrot_mc/colors.py
carrot_mc/data.py
carrot_mc/meta.py
carrot_mc/model.py
carrot_mc/web_gui/__init__.py
carrot_mc/web_gui/app.py
carrot_mc/web_gui/static/main.css
carrot_mc/web_gui/static/main.css.map
carrot_mc/web_gui/static/main.js
carrot_mc/web_gui/static/main.js.map
carrot_mc/web_gui/static/img/Eclipse_loading.svg
carrot_mc/web_gui/static/img/Spin_loading.svg
carrot_mc/web_gui/static/img/carrot.png
carrot_mc/web_gui/templates/index.html
carrot_mc-0.5.3.dist-info/LICENSE
carrot_mc-0.5.3.dist-info/METADATA
carrot_mc-0.5.3.dist-info/WHEEL
carrot_mc-0.5.3.dist-info/entry_points.txt
carrot_mc-0.5.3.dist-info/top_level.txt
carrot_mc-0.5.3.dist-info/RECORD
