Metadata-Version: 2.1
Name: carrot-mc
Version: 0.5.3
Summary: Command-line Minecraft mod manager
Home-page: https://github.com/Misza13/carrot
Author: Misza
Author-email: misza@misza.net
License: MIT
Platform: UNKNOWN
Classifier: Programming Language :: Python :: 3
Classifier: Programming Language :: Python :: 3.6
Classifier: Topic :: Games/Entertainment
Requires-Dist: requests
Requires-Dist: Flask
Requires-Dist: Flask-SocketIO
Requires-Dist: eventlet
